pidfile/__init__.py
pidfile/pidfile.py
pidfile/version.py
python_pidfile-3.1.1.dist-info/LICENSE
python_pidfile-3.1.1.dist-info/METADATA
python_pidfile-3.1.1.dist-info/WHEEL
python_pidfile-3.1.1.dist-info/top_level.txt
python_pidfile-3.1.1.dist-info/RECORD
