Metadata-Version: 2.1
Name: python-pidfile
Version: 3.1.1
Summary: PIDFile context manager.
Home-page: https://github.com/mosquito/python-pidfile
Author: Dmitry Orlov <me@mosquito.su>, Costantino Grana <None>, Lorenzo Baraldi <None>, Michele Cancilla <None>
Author-email: me@mosquito.su
License: MIT
Platform: unix
Classifier: Development Status :: 5 - Production/Stable
Classifier: Natural Language :: English
Classifier: Operating System :: MacOS
Classifier: Operating System :: POSIX
Classifier: Programming Language :: Python :: 3
Classifier: Programming Language :: Python :: 3.7
Classifier: Programming Language :: Python :: 3.8
Classifier: Programming Language :: Python :: 3.9
Classifier: Programming Language :: Python :: 3.10
Classifier: Programming Language :: Python :: 3.11
Classifier: Programming Language :: Python :: Implementation :: CPython
Classifier: License :: OSI Approved :: MIT License
License-File: LICENSE
Requires-Dist: psutil
Provides-Extra: develop
Requires-Dist: coverage (!=4.3) ; extra == 'develop'
Requires-Dist: coveralls ; extra == 'develop'
Requires-Dist: pylama ; extra == 'develop'
Requires-Dist: pytest ; extra == 'develop'
Requires-Dist: pytest-cov ; extra == 'develop'
Requires-Dist: mock ; extra == 'develop'
